zeppos_sandbox/__init__.py
zeppos_sandbox/demo.py
zeppos_sandbox-0.0.1.dist-info/LICENSE
zeppos_sandbox-0.0.1.dist-info/METADATA
zeppos_sandbox-0.0.1.dist-info/WHEEL
zeppos_sandbox-0.0.1.dist-info/top_level.txt
zeppos_sandbox-0.0.1.dist-info/RECORD
