Metadata-Version: 2.1
Name: zeppos-sandbox
Version: 0.0.1
Summary: Zeppos Pypi project template
Author-email: Papa Bear Codes Python <PapaBearCodesPython@gmail.com>
License: Apache License
Keywords: pypi,template,zeppos
Classifier: Programming Language :: Python :: 3
Requires-Python: >=3.8
License-File: LICENSE
Provides-Extra: development
Requires-Dist: anybadge ==1.14.0 ; extra == 'development'
Requires-Dist: astroid ==3.0.1 ; extra == 'development'
Requires-Dist: black ==23.11.0 ; extra == 'development'
Requires-Dist: build ==1.0.3 ; extra == 'development'
Requires-Dist: click ==8.1.7 ; extra == 'development'
Requires-Dist: coverage ==7.3.2 ; extra == 'development'
Requires-Dist: dill ==0.3.7 ; extra == 'development'
Requires-Dist: importlib-metadata ==7.0.0 ; extra == 'development'
Requires-Dist: iniconfig ==2.0.0 ; extra == 'development'
Requires-Dist: isort ==5.12.0 ; extra == 'development'
Requires-Dist: jinja2 ==3.1.2 ; extra == 'development'
Requires-Dist: markupsafe ==2.1.3 ; extra == 'development'
Requires-Dist: mccabe ==0.7.0 ; extra == 'development'
Requires-Dist: mypy ==1.7.1 ; extra == 'development'
Requires-Dist: mypy-extensions ==1.0.0 ; extra == 'development'
Requires-Dist: packaging ==23.2 ; extra == 'development'
Requires-Dist: pathspec ==0.11.2 ; extra == 'development'
Requires-Dist: pip-tools ==7.3.0 ; extra == 'development'
Requires-Dist: pipdeptree ==2.13.1 ; extra == 'development'
Requires-Dist: platformdirs ==4.1.0 ; extra == 'development'
Requires-Dist: pluggy ==1.3.0 ; extra == 'development'
Requires-Dist: pydocstyle ==6.3.0 ; extra == 'development'
Requires-Dist: pylint ==3.0.2 ; extra == 'development'
Requires-Dist: pylint-gitlab ==2.0.0 ; extra == 'development'
Requires-Dist: pyproject-hooks ==1.0.0 ; extra == 'development'
Requires-Dist: pytest ==7.4.3 ; extra == 'development'
Requires-Dist: pytest-cov ==4.1.0 ; extra == 'development'
Requires-Dist: setuptools-scm ==8.0.4 ; extra == 'development'
Requires-Dist: snowballstemmer ==2.2.0 ; extra == 'development'
Requires-Dist: toml ==0.10.2 ; extra == 'development'
Requires-Dist: tomli ==2.0.1 ; extra == 'development'
Requires-Dist: tomlkit ==0.12.3 ; extra == 'development'
Requires-Dist: typing-extensions ==4.8.0 ; extra == 'development'
Requires-Dist: update-toml ==0.0.3 ; extra == 'development'
Requires-Dist: wheel ==0.42.0 ; extra == 'development'
Requires-Dist: wrapt ==1.16.0 ; extra == 'development'
Requires-Dist: zipp ==3.17.0 ; extra == 'development'
Requires-Dist: pip ==23.3.1 ; extra == 'development'
Requires-Dist: setuptools ==69.0.2 ; extra == 'development'
